decavision/__init__.py
decavision/dataset_preparation/__init__.py
decavision/dataset_preparation/data_augmentation.py
decavision/dataset_preparation/generate_pseudolabels.py
decavision/dataset_preparation/generate_tfrecords.py
decavision/model_testing/__init__.py
decavision/model_testing/testing.py
decavision/model_training/__init__.py
decavision/model_training/progressive_learning.py
decavision/model_training/tfrecords_image_classifier.py
decavision/utils/__init__.py
decavision/utils/colab_utils.py
decavision/utils/data_utils.py
decavision/utils/training_utils.py
decavision/utils/utils.py
decavision-1.4.2.dist-info/LICENSE
decavision-1.4.2.dist-info/METADATA
decavision-1.4.2.dist-info/WHEEL
decavision-1.4.2.dist-info/top_level.txt
decavision-1.4.2.dist-info/RECORD
