Metadata-Version: 2.1
Name: decavision
Version: 1.4.2
Summary: A package to easily train powerful image classification models using colab's free TPUs.
Home-page: https://github.com/Decathlon/decavision.git
Author: Décathlon Canada
Author-email: sportvisionapi@decathlon.com
License: UNKNOWN
Platform: UNKNOWN
Classifier: Programming Language :: Python :: 3
Classifier: License :: OSI Approved :: MIT License
Classifier: Operating System :: OS Independent
Requires-Python: >=3.6
Requires-Dist: augmentor (==0.2.8)
Requires-Dist: dill (==0.3.2)
Requires-Dist: google-cloud-storage (==1.31.2)
Requires-Dist: matplotlib (==3.3.2)
Requires-Dist: numpy (==1.21.6)
Requires-Dist: pandas (==1.1.3)
Requires-Dist: patool (==1.12)
Requires-Dist: pillow (==9.0.1)
Requires-Dist: pyunpack (==0.2.2)
Requires-Dist: scikit-learn (==0.23.2)
Requires-Dist: scikit-optimize (==0.8.1)
Requires-Dist: seaborn (==0.11.0)
Requires-Dist: tqdm (==4.60.0)
